pdf_liner/__init__.py
pdf_liner/__main__.py
pdf_liner/arg_parser.py
pdf_liner/constants.py
pdf_liner-0.1.0.dist-info/METADATA
pdf_liner-0.1.0.dist-info/WHEEL
pdf_liner-0.1.0.dist-info/entry_points.txt
pdf_liner-0.1.0.dist-info/RECORD
