Metadata-Version: 2.4
Name: pdf-liner
Version: 0.1.0
Summary: A simple Python tool that adds equally spaced horizontal lines to PDF files, making them perfect for printing and handwriting
License-Expression: MIT
Keywords: pdf,lines,handwriting,notes,printing
Author: raideno56
Author-email: nadirkichou@hotmail.fr
Requires-Python: >=3.9,<4
Classifier: Development Status :: 4 - Beta
Classifier: Intended Audience :: End Users/Desktop
Classifier: Topic :: Office/Business
Classifier: Topic :: Utilities
Classifier: Programming Language :: Python :: 3
Classifier: Programming Language :: Python :: 3.9
Classifier: Programming Language :: Python :: 3.10
Classifier: Programming Language :: Python :: 3.11
Classifier: Programming Language :: Python :: 3.12
Requires-Dist: pypdf2 (>=3.0.1)
Requires-Dist: reportlab (>=4.0.7)
Project-URL: Homepage, https://github.com/raideno/pdf-liner
Project-URL: Repository, https://github.com/raideno/pdf-liner
